stripe_bulk_promocode_generator/__init__.py
stripe_bulk_promocode_generator/main.py
stripe_bulk_promocode_generator-0.2.0.dist-info/METADATA
stripe_bulk_promocode_generator-0.2.0.dist-info/WHEEL
stripe_bulk_promocode_generator-0.2.0.dist-info/entry_points.txt
stripe_bulk_promocode_generator-0.2.0.dist-info/licenses/LICENSE
stripe_bulk_promocode_generator-0.2.0.dist-info/RECORD
