Metadata-Version: 2.4
Name: stripe-bulk-promocode-generator
Version: 0.2.0
Summary: A tool to generate multiple Stripe promotion codes in bulk
Author-email: Luke Harries <lharries@users.noreply.github.com>
License-File: LICENSE
Classifier: License :: OSI Approved :: MIT License
Classifier: Operating System :: OS Independent
Classifier: Programming Language :: Python :: 3
Requires-Python: >=3.11
Requires-Dist: python-dotenv
Requires-Dist: stripe
